spice_shyla/__init__.py
spice_shyla/inversion.py
spice_shyla/pykonal_plotter.py
spice_shyla/spice.py
spice_shyla/spicey_plotter.py
spice_shyla-0.1.0.dist-info/METADATA
spice_shyla-0.1.0.dist-info/WHEEL
spice_shyla-0.1.0.dist-info/licenses/LICENSE.rtf
spice_shyla-0.1.0.dist-info/RECORD
