Metadata-Version: 2.4
Name: spice_shyla
Version: 0.1.0
Summary: A modular-based Python package for shallow diving-wave analysis of hammer seismics
Project-URL: Homepage, https://github.com/shylarae10/SPIce
Project-URL: Repository, https://github.com/shylarae10/SPIce
Author-email: Shyla Kupis <shyla.kupis@utas.edu.au>
License-Expression: MIT
License-File: LICENSE.rtf
Classifier: Development Status :: 3 - Alpha
Classifier: Intended Audience :: Science/Research
Classifier: Programming Language :: Python :: 3
Classifier: Programming Language :: Python :: 3.8
Classifier: Programming Language :: Python :: 3.9
Classifier: Programming Language :: Python :: 3.10
Classifier: Programming Language :: Python :: 3.11
Classifier: Topic :: Scientific/Engineering :: Physics
Requires-Python: >=3.8
Requires-Dist: matplotlib>=3.4.0
Requires-Dist: numpy>=1.21.0
Requires-Dist: obspy>=1.3.0
Requires-Dist: pandas>=1.3.0
Requires-Dist: pykonal>=0.3.0
Requires-Dist: pyproj>=3.0.0
Requires-Dist: scipy>=1.7.0
Provides-Extra: dev
Requires-Dist: black>=22.0; extra == 'dev'
Requires-Dist: flake8>=4.0; extra == 'dev'
Requires-Dist: pytest>=7.0; extra == 'dev'
